rave_python/__init__.py
rave_python/rave.py
rave_python/rave_account.py
rave_python/rave_applepay.py
rave_python/rave_banktransfer.py
rave_python/rave_base.py
rave_python/rave_bills.py
rave_python/rave_card.py
rave_python/rave_ebills.py
rave_python/rave_enaira.py
rave_python/rave_exceptions.py
rave_python/rave_fawrypay.py
rave_python/rave_francophone.py
rave_python/rave_ghmobile.py
rave_python/rave_googlepay.py
rave_python/rave_misc.py
rave_python/rave_mpesa.py
rave_python/rave_payment.py
rave_python/rave_paymentplan.py
rave_python/rave_preauth.py
rave_python/rave_recepient.py
rave_python/rave_recipient.py
rave_python/rave_rwmobile.py
rave_python/rave_settlement.py
rave_python/rave_subaccounts.py
rave_python/rave_subscription.py
rave_python/rave_transfer.py
rave_python/rave_tzmobile.py
rave_python/rave_ugmobile.py
rave_python/rave_ussd.py
rave_python/rave_verify.py
rave_python/rave_virtualaccount.py
rave_python/rave_virtualcard.py
rave_python/rave_zbmobile.py
rave_python-1.4.2.dist-info/LICENSE
rave_python-1.4.2.dist-info/METADATA
rave_python-1.4.2.dist-info/WHEEL
rave_python-1.4.2.dist-info/top_level.txt
rave_python-1.4.2.dist-info/RECORD
